ssmpy/__init__.py
ssmpy/annotations.py
ssmpy/calculations.py
ssmpy/data.py
ssmpy/metrics.py
ssmpy/semanticbase.py
ssmpy/ssm.py
ssmpy-0.2.7.dist-info/LICENSE
ssmpy-0.2.7.dist-info/METADATA
ssmpy-0.2.7.dist-info/NOTICE.txt
ssmpy-0.2.7.dist-info/WHEEL
ssmpy-0.2.7.dist-info/top_level.txt
ssmpy-0.2.7.dist-info/RECORD
