Metadata-Version: 2.1
Name: ssmpy
Version: 0.2.7
Summary: Basic functions to start using semantic similarity measures directly from a rdf or owl file.
Home-page: https://github.com/lasigeBioTM/DiShIn
Author: Andre Lamurias
Author-email: alamurias@lasige.di.fc.ul.pt
Maintainer: Francisco M Couto
Maintainer-email: fjcouto@ciencias.ulisboa.pt
License: UNKNOWN
Keywords: graphs,semantic similarity,ontologies
Platform: UNKNOWN
Classifier: Programming Language :: Python :: 3
Classifier: License :: OSI Approved :: MIT License
Classifier: Operating System :: OS Independent
Requires-Dist: rdflib
Requires-Dist: numpy (<=1.19.5,>=1.18.5) ; python_version < "3.8"
Requires-Dist: pandas ; python_version >= "3.8"
Requires-Dist: sqlite3 ; python_version >= "3.8"
Requires-Dist: math ; python_version >= "3.8"
Requires-Dist: multiprocessing ; python_version >= "3.8"
Requires-Dist: numpy (>=1.19.5) ; python_version >= "3.8"
